bruhanimate/__init__.py
bruhanimate/bruheffect/__init__.py
bruhanimate/bruheffect/base_effect.py
bruhanimate/bruheffect/chatbot_effect.py
bruhanimate/bruheffect/draw_lines_effect.py
bruhanimate/bruheffect/fire_effect.py
bruhanimate/bruheffect/firework_effect.py
bruhanimate/bruheffect/game_of_life_effect.py
bruhanimate/bruheffect/julia_effect.py
bruhanimate/bruheffect/matrix_effect.py
bruhanimate/bruheffect/noise_effect.py
bruhanimate/bruheffect/offset_effect.py
bruhanimate/bruheffect/plasma_effect.py
bruhanimate/bruheffect/rain_effect.py
bruhanimate/bruheffect/snow_effect.py
bruhanimate/bruheffect/star_effect.py
bruhanimate/bruheffect/static_effect.py
bruhanimate/bruheffect/twinkle_effect.py
bruhanimate/bruheffect/water_effect.py
bruhanimate/bruhrenderer/__init__.py
bruhanimate/bruhrenderer/background_color_renderer.py
bruhanimate/bruhrenderer/base_renderer.py
bruhanimate/bruhrenderer/center_renderer.py
bruhanimate/bruhrenderer/effect_renderer.py
bruhanimate/bruhrenderer/focus_renderer.py
bruhanimate/bruhrenderer/pan_renderer.py
bruhanimate/bruhutil/__init__.py
bruhanimate/bruhutil/bruherrors.py
bruhanimate/bruhutil/bruhffer.py
bruhanimate/bruhutil/bruhimage.py
bruhanimate/bruhutil/bruhscreen.py
bruhanimate/bruhutil/bruhtypes.py
bruhanimate/bruhutil/utils.py
bruhanimate/demos/__init__.py
bruhanimate/demos/chatbot_demo.py
bruhanimate/demos/fire_demo.py
bruhanimate/demos/firework_demo.py
bruhanimate/demos/gol_demo.py
bruhanimate/demos/holiday.py
bruhanimate/demos/julia_demo.py
bruhanimate/demos/line_demo.py
bruhanimate/demos/matrix_demo.py
bruhanimate/demos/noise_demo.py
bruhanimate/demos/offset_demo.py
bruhanimate/demos/plasma_demo.py
bruhanimate/demos/rain_demo.py
bruhanimate/demos/snow_demo.py
bruhanimate/demos/stars_demo.py
bruhanimate/demos/static_demo.py
bruhanimate/demos/twinkle_demo.py
bruhanimate-0.2.96.dist-info/licenses/COPYING
bruhanimate-0.2.96.dist-info/licenses/LICENSE
bruhanimate-0.2.96.dist-info/METADATA
bruhanimate-0.2.96.dist-info/WHEEL
bruhanimate-0.2.96.dist-info/RECORD
