Metadata-Version: 2.4
Name: bruhanimate
Version: 0.2.96
Summary: ASCII Termnial Animation Package
License: Apache License
License-File: COPYING
License-File: LICENSE
Keywords: python,terminal,terminal-animation,bruhanimate
Author: ethanlchristensen
Author-email: ethanlchristensen@outlook.com
Requires-Python: >=3.13,<4.0
Classifier: Development Status :: 4 - Beta
Classifier: Intended Audience :: Developers
Classifier: License :: Other/Proprietary License
Classifier: Operating System :: Microsoft :: Windows
Classifier: Operating System :: Unix
Classifier: Programming Language :: Python :: 3
Classifier: Programming Language :: Python :: 3.13
Classifier: Programming Language :: Python :: 3.14
Requires-Dist: bruhcolor (>=0.0.64,<0.0.65)
Requires-Dist: future (>=1.0.0,<2.0.0)
Requires-Dist: numpy (>=2.3.4,<3.0.0)
Requires-Dist: openai (>=2.6.1,<3.0.0)
Requires-Dist: pyfiglet (>=1.0.4,<2.0.0)
Requires-Dist: pywin32 (>=311,<312) ; sys_platform == "win32"
Requires-Dist: requests (>=2.32.5,<3.0.0)
Project-URL: Homepage, https://github.com/ethanlchristensen/bruhanimate
Project-URL: Repository, https://github.com/ethanlchristensen/bruhanimate
